mlexec/__init__.py
mlexec/execution.py
mlexec/version.py
mlexec-0.0.2.dist-info/LICENSE
mlexec-0.0.2.dist-info/METADATA
mlexec-0.0.2.dist-info/WHEEL
mlexec-0.0.2.dist-info/top_level.txt
mlexec-0.0.2.dist-info/RECORD
