Metadata-Version: 2.1
Name: mlexec
Version: 0.0.2
Summary: The mlexec package is used to run scikit-learn type models with high abstraction.
Author: DivM11
License: MIT
Platform: unix
Platform: linux
Platform: osx
Platform: cygwin
Platform: win32
Classifier: Programming Language :: Python :: 3
Classifier: Programming Language :: Python :: 3 :: Only
Classifier: Programming Language :: Python :: 3.9
Classifier: Programming Language :: Python :: 3.10
Requires-Python: >=3.9
License-File: LICENSE
Requires-Dist: pandas
Requires-Dist: matplotlib
Requires-Dist: hyperopt
Requires-Dist: scikit-learn
Requires-Dist: lightgbm
Requires-Dist: xgboost
Requires-Dist: tensorflow
Provides-Extra: testing
Requires-Dist: pytest ; extra == 'testing'
Requires-Dist: pytest-cov ; extra == 'testing'
Requires-Dist: mypy ; extra == 'testing'
Requires-Dist: tox ; extra == 'testing'
